{
    "columns":[
        "computer_id",
        "room",
        "system_unit",
        "monitor",
        "has_mouse",
        "has_keyboard",
        "has_internet",
        "has_software",
        "status",
        "condition_id",
        "building_code"
    ],
    "rows": [
        {
          "computer_id": 1289,
          "room": 408,
          "system_unit": "SYU-1289",
          "monitor": "MON-101",
          "has_mouse": 1,
          "has_keyboard": 1,
          "has_internet": 1,
          "has_software": 1,
          "status": 1,
          "condition_id": 1,
          "building_code": "MB"
        },
        {
          "computer_id": 1290,
          "room": 408,
          "system_unit": "SYU-1290",
          "monitor": "MON-102",
          "has_mouse": 1,
          "has_keyboard": 1,
          "has_internet": 1,
          "has_software": 1,
          "status": 1,
          "condition_id": 2,
          "building_code": "MB"
        },
        {
          "computer_id": 1291,
          "room": 408,
          "system_unit": "SYU-1291",
          "monitor": "MON-103",
          "has_mouse": 1,
          "has_keyboard": 1,
          "has_internet": 1,
          "has_software": 0,
          "status": 1,
          "condition_id": 3,
          "building_code": "MB"
        },
        {
          "computer_id": 2003,
          "room": 515,
          "system_unit": "SYU-2003",
          "monitor": "MON-205",
          "has_mouse": 1,
          "has_keyboard": 1,
          "has_internet": 1,
          "has_software": 0,
          "status": 1,
          "condition_id": 3,
          "building_code": "ANB"
        },
        {
          "computer_id": 2004,
          "room": 515,
          "system_unit": "SYU-2004",
          "monitor": "MON-206",
          "has_mouse": 0,
          "has_keyboard": 0,
          "has_internet": 1,
          "has_software": 1,
          "status": 0,
          "condition_id": 2,
          "building_code": "ANB"
        },
        {
          "computer_id": 2005,
          "room": 515,
          "system_unit": "SYU-2005",
          "monitor": "MON-207",
          "has_mouse": 1,
          "has_keyboard": 0,
          "has_internet": 1,
          "has_software": 1,
          "status": 1,
          "condition_id": 1,
          "building_code": "MB"
        },
        {
          "computer_id": 2056,
          "room": 610,
          "system_unit": "SYU-2056",
          "monitor": "MON-309",
          "has_mouse": 0,
          "has_keyboard": 0,
          "has_internet": 1,
          "has_software": 1,
          "status": 0,
          "condition_id": 0,
          "building_code": "ANB"
        },
        {
          "computer_id": 2057,
          "room": 610,
          "system_unit": "SYU-2057",
          "monitor": "MON-310",
          "has_mouse": 1,
          "has_keyboard": 1,
          "has_internet": 1,
          "has_software": 0,
          "status": 1,
          "condition_id": 3,
          "building_code": "MB"
        },
        {
          "computer_id": 2058,
          "room": 610,
          "system_unit": "SYU-2058",
          "monitor": "MON-311",
          "has_mouse": 1,
          "has_keyboard": 0,
          "has_internet": 1,
          "has_software": 0,
          "status": 1,
          "condition_id": 3,
          "building_code": "MB"
        },
        {
          "computer_id": 1292,
          "room": 408,
          "system_unit": "SYU-1292",
          "monitor": "MON-104",
          "has_mouse": 1,
          "has_keyboard": 1,
          "has_internet": 1,
          "has_software": 1,
          "status": 1,
          "condition_id": 1,
          "building_code": "MB"
        },
        {
          "computer_id": 1293,
          "room": 408,
          "system_unit": "SYU-1293",
          "monitor": "MON-105",
          "has_mouse": 1,
          "has_keyboard": 1,
          "has_internet": 1,
          "has_software": 1,
          "status": 1,
          "condition_id": 2,
          "building_code": "MB"
        },
        {
          "computer_id": 1294,
          "room": 408,
          "system_unit": "SYU-1294",
          "monitor": "MON-106",
          "has_mouse": 1,
          "has_keyboard": 1,
          "has_internet": 1,
          "has_software": 1,
          "status": 1,
          "condition_id": 1,
          "building_code": "MB"
        },
        {
          "computer_id": 1295,
          "room": 408,
          "system_unit": "SYU-1295",
          "monitor": "MON-107",
          "has_mouse": 1,
          "has_keyboard": 1,
          "has_internet": 1,
          "has_software": 1,
          "status": 1,
          "condition_id": 2,
          "building_code": "MB"
        },
        {
          "computer_id": 1296,
          "room": 408,
          "system_unit": "SYU-1296",
          "monitor": "MON-108",
          "has_mouse": 1,
          "has_keyboard": 1,
          "has_internet": 1,
          "has_software": 1,
          "status": 1,
          "condition_id": 3,
          "building_code": "MB"
        },
        {
          "computer_id": 1297,
          "room": 408,
          "system_unit": "SYU-1297",
          "monitor": "MON-109",
          "has_mouse": 1,
          "has_keyboard": 1,
          "has_internet": 1,
          "has_software": 1,
          "status": 1,
          "condition_id": 0,
          "building_code": "MB"
        },
        {
          "computer_id": 1298,
          "room": 408,
          "system_unit": "SYU-1298",
          "monitor": "MON-110",
          "has_mouse": 1,
          "has_keyboard": 1,
          "has_internet": 1,
          "has_software": 1,
          "status": 1,
          "condition_id": 1,
          "building_code": "MB"
        },
        {
          "computer_id": 1299,
          "room": 408,
          "system_unit": "SYU-1299",
          "monitor": "MON-111",
          "has_mouse": 1,
          "has_keyboard": 1,
          "has_internet": 1,
          "has_software": 1,
          "status": 1,
          "condition_id": 2,
          "building_code": "MB"
        },
        {
          "computer_id": 1300,
          "room": 408,
          "system_unit": "SYU-1300",
          "monitor": "MON-112",
          "has_mouse": 1,
          "has_keyboard": 1,
          "has_internet": 1,
          "has_software": 1,
          "status": 1,
          "condition_id": 3,
          "building_code": "MB"
        },
        {
          "computer_id": 1301,
          "room": 408,
          "system_unit": "SYU-1301",
          "monitor": "MON-113",
          "has_mouse": 1,
          "has_keyboard": 1,
          "has_internet": 1,
          "has_software": 1,
          "status": 1,
          "condition_id": 0,
          "building_code": "MB"
        },
        {
          "computer_id": 1302,
          "room": 408,
          "system_unit": "SYU-1302",
          "monitor": "MON-114",
          "has_mouse": 1,
          "has_keyboard": 1,
          "has_internet": 1,
          "has_software": 1,
          "status": 1,
          "condition_id": 1,
          "building_code": "MB"
        },
        {
          "computer_id": 1303,
          "room": 408,
          "system_unit": "SYU-1303",
          "monitor": "MON-115",
          "has_mouse": 1,
          "has_keyboard": 1,
          "has_internet": 1,
          "has_software": 1,
          "status": 1,
          "condition_id": 2,
          "building_code": "MB"
        },
        {
          "computer_id": 1304,
          "room": 408,
          "system_unit": "SYU-1304",
          "monitor": "MON-116",
          "has_mouse": 1,
          "has_keyboard": 1,
          "has_internet": 1,
          "has_software": 1,
          "status": 1,
          "condition_id": 3,
          "building_code": "MB"
        },
        {
          "computer_id": 1305,
          "room": 408,
          "system_unit": "SYU-1305",
          "monitor": "MON-117",
          "has_mouse": 1,
          "has_keyboard": 1,
          "has_internet": 1,
          "has_software": 1,
          "status": 1,
          "condition_id": 0,
          "building_code": "MB"
        },
        {
          "computer_id": 1306,
          "room": 408,
          "system_unit": "SYU-1306",
          "monitor": "MON-118",
          "has_mouse": 1,
          "has_keyboard": 1,
          "has_internet": 1,
          "has_software": 1,
          "status": 1,
          "condition_id": 1,
          "building_code": "MB"
        },
        {
          "computer_id": 1307,
          "room": 408,
          "system_unit": "SYU-1307",
          "monitor": "MON-119",
          "has_mouse": 1,
          "has_keyboard": 1,
          "has_internet": 1,
          "has_software": 1,
          "status": 1,
          "condition_id": 2,
          "building_code": "MB"
        },
        {
          "computer_id": 1308,
          "room": 408,
          "system_unit": "SYU-1308",
          "monitor": "MON-120",
          "has_mouse": 1,
          "has_keyboard": 1,
          "has_internet": 1,
          "has_software": 1,
          "status": 1,
          "condition_id": 3,
          "building_code": "MB"
        },
        {
          "computer_id": 1309,
          "room": 408,
          "system_unit": "SYU-1309",
          "monitor": "MON-121",
          "has_mouse": 1,
          "has_keyboard": 1,
          "has_internet": 1,
          "has_software": 1,
          "status": 1,
          "condition_id": 0,
          "building_code": "MB"
        },
        {
          "computer_id": 1310,
          "room": 408,
          "system_unit": "SYU-1310",
          "monitor": "MON-122",
          "has_mouse": 1,
          "has_keyboard": 1,
          "has_internet": 1,
          "has_software": 1,
          "status": 1,
          "condition_id": 1,
          "building_code": "MB"
        },
        {
          "computer_id": 1311,
          "room": 408,
          "system_unit": "SYU-1311",
          "monitor": "MON-123",
          "has_mouse": 1,
          "has_keyboard": 1,
          "has_internet": 1,
          "has_software": 1,
          "status": 1,
          "condition_id": 2,
          "building_code": "MB"
        },
        {
          "computer_id": 1312,
          "room": 408,
          "system_unit": "SYU-1312",
          "monitor": "MON-124",
          "has_mouse": 1,
          "has_keyboard": 1,
          "has_internet": 1,
          "has_software": 1,
          "status": 1,
          "condition_id": 3,
          "building_code": "MB"
        },
        {
          "computer_id": 1313,
          "room": 408,
          "system_unit": "SYU-1313",
          "monitor": "MON-125",
          "has_mouse": 1,
          "has_keyboard": 1,
          "has_internet": 1,
          "has_software": 1,
          "status": 1,
          "condition_id": 0,
          "building_code": "MB"
        },
        {
          "computer_id": 2059,
          "room": 611,
          "system_unit": "SYU-2059",
          "monitor": "MON-312",
          "has_mouse": 1,
          "has_keyboard": 1,
          "has_internet": 1,
          "has_software": 1,
          "status": 1,
          "condition_id": 2,
          "building_code": "ANB"
        },
        {
          "computer_id": 2060,
          "room": 611,
          "system_unit": "SYU-2060",
          "monitor": "MON-313",
          "has_mouse": 1,
          "has_keyboard": 0,
          "has_internet": 1,
          "has_software": 0,
          "status": 0,
          "condition_id": 3,
          "building_code": "ANB"
        },
        {
          "computer_id": 2061,
          "room": 612,
          "system_unit": "SYU-2061",
          "monitor": "MON-314",
          "has_mouse": 0,
          "has_keyboard": 1,
          "has_internet": 1,
          "has_software": 1,
          "status": 1,
          "condition_id": 1,
          "building_code": "ANB"
        },
        {
          "computer_id": 2062,
          "room": 612,
          "system_unit": "SYU-2062",
          "monitor": "MON-315",
          "has_mouse": 1,
          "has_keyboard": 1,
          "has_internet": 1,
          "has_software": 0,
          "status": 1,
          "condition_id": 0,
          "building_code": "ANB"
        },
        {
          "computer_id": 2063,
          "room": 613,
          "system_unit": "SYU-2063",
          "monitor": "MON-316",
          "has_mouse": 1,
          "has_keyboard": 1,
          "has_internet": 1,
          "has_software": 1,
          "status": 1,
          "condition_id": 1,
          "building_code": "ANB"
        },
        {
          "computer_id": 2064,
          "room": 613,
          "system_unit": "SYU-2064",
          "monitor": "MON-317",
          "has_mouse": 0,
          "has_keyboard": 0,
          "has_internet": 1,
          "has_software": 0,
          "status": 0,
          "condition_id": 2,
          "building_code": "ANB"
        },
        {
          "computer_id": 2065,
          "room": 614,
          "system_unit": "SYU-2065",
          "monitor": "MON-318",
          "has_mouse": 1,
          "has_keyboard": 1,
          "has_internet": 1,
          "has_software": 1,
          "status": 1,
          "condition_id": 3,
          "building_code": "ANB"
        },
        {
          "computer_id": 2066,
          "room": 614,
          "system_unit": "SYU-2066",
          "monitor": "MON-319",
          "has_mouse": 1,
          "has_keyboard": 0,
          "has_internet": 1,
          "has_software": 0,
          "status": 1,
          "condition_id": 0,
          "building_code": "ANB"
        },
        {
          "computer_id": 2067,
          "room": 615,
          "system_unit": "SYU-2067",
          "monitor": "MON-320",
          "has_mouse": 0,
          "has_keyboard": 1,
          "has_internet": 1,
          "has_software": 1,
          "status": 1,
          "condition_id": 2,
          "building_code": "ANB"
        }
    ]
}